example_package_visiblent/__init__.py
example_package_visiblent/main.py
example_package_visiblent-0.0.3.dist-info/METADATA
example_package_visiblent-0.0.3.dist-info/WHEEL
example_package_visiblent-0.0.3.dist-info/licenses/LICENSE
example_package_visiblent-0.0.3.dist-info/RECORD
