Metadata-Version: 2.1
Name: example_package_visiblent
Version: 0.0.3
Summary: A small example package
Project-URL: Homepage, https://github.com/visiblent/example_package_visiblent
Project-URL: Repository, https://github.com/visiblent/example_package_visiblent.git
Project-URL: Source, https://github.com/visiblent/example_package_visiblent
Author-email: visiblent <sind.b.7@gmail.com>
License-File: LICENSE
Classifier: License :: OSI Approved :: MIT License
Classifier: Operating System :: OS Independent
Classifier: Programming Language :: Python :: 3
Requires-Python: >=3.8
Requires-Dist: requests
